{"cameraMode":{"drawMode":0,"name":"Shaded","section":"Shading Mode"},"sceneLighting":true,"audioPlay":false,"sceneViewState":{"m_AlwaysRefresh":false,"showFog":true,"showSkybox":true,"showFlares":true,"showImageEffects":true,"showParticleSystems":true,"showVisualEffectGraphs":true,"m_FxEnabled":true},"in2DMode":false,"pivot":{"x":2.0836057662963869,"y":1.6035077571868897,"z":3.149552345275879},"rotation":{"x":0.15629251301288606,"y":-0.2816636264324188,"z":0.046563178300857547,"w":0.9455700516700745},"size":0.05357854440808296,"orthographic":false}